README.md
setup.cfg
setup.py
fcryptor/__init__.py
fcryptor/fcryptor.py
fcryptor.egg-info/PKG-INFO
fcryptor.egg-info/SOURCES.txt
fcryptor.egg-info/dependency_links.txt
fcryptor.egg-info/entry_points.txt
fcryptor.egg-info/requires.txt
fcryptor.egg-info/top_level.txt