Metadata-Version: 2.1
Name: fcryptor
Version: 1.0.6
Summary: python package that encrypt/decrypt files by key.
Home-page: https://github.com/omidekz/fcryptor
Author: Omid Karimzade
Author-email: omidekz@gmail.com
License: MIT
Keywords: file encryptor,file cryptography,file crypt,decrypt,fcryptor,file-cryptor
Platform: UNKNOWN
Classifier: Development Status :: 3 - Alpha
Classifier: Intended Audience :: Developers
Classifier: Topic :: Security :: Cryptography
Classifier: License :: OSI Approved :: MIT License
Classifier: Programming Language :: Python :: 3
Classifier: Programming Language :: Python :: 3.0
Classifier: Programming Language :: Python :: 3.1
Classifier: Programming Language :: Python :: 3.10
Classifier: Programming Language :: Python :: 3.2
Classifier: Programming Language :: Python :: 3.3
Classifier: Programming Language :: Python :: 3.4
Classifier: Programming Language :: Python :: 3.5
Classifier: Programming Language :: Python :: 3.6
Classifier: Programming Language :: Python :: 3.7
Classifier: Programming Language :: Python :: 3.8
Classifier: Programming Language :: Python :: 3.9
